asimov_nearai_prompter/__init__.py
asimov_nearai_prompter/__main__.py
asimov_nearai_module-0.0.0.dist-info/METADATA
asimov_nearai_module-0.0.0.dist-info/WHEEL
asimov_nearai_module-0.0.0.dist-info/entry_points.txt
asimov_nearai_module-0.0.0.dist-info/top_level.txt
asimov_nearai_module-0.0.0.dist-info/RECORD
