Metadata-Version: 2.2
Name: asimov-nearai-module
Version: 0.0.0
Summary: ASIMOV NEAR AI Module
Author-email: ASIMOV Protocol <support@asimov.so>
License: Unlicense
Project-URL: Homepage, https://github.com/asimov-modules/asimov-nearai-module
Project-URL: Documentation, https://github.com/asimov-modules/asimov-nearai-module
Project-URL: Repository, https://github.com/asimov-modules/asimov-nearai-module.git
Project-URL: Issues, https://github.com/asimov-modules/asimov-nearai-module/issues
Project-URL: Changelog, https://github.com/asimov-modules/asimov-nearai-module/blob/master/CHANGES.md
Classifier: Development Status :: 3 - Alpha
Classifier: Environment :: Console
Classifier: Environment :: MacOS X
Classifier: Intended Audience :: Developers
Classifier: License :: OSI Approved :: The Unlicense (Unlicense)
Classifier: License :: Public Domain
Classifier: Operating System :: MacOS :: MacOS X
Classifier: Programming Language :: Python :: 3
Classifier: Programming Language :: Python :: 3.13
Classifier: Programming Language :: Python :: 3.14
Classifier: Topic :: Scientific/Engineering :: Artificial Intelligence
Classifier: Topic :: Text Processing :: General
Requires-Python: >=3.13
Requires-Dist: nearai>=0.1.12
